{
  "id": "f52daf1e-5f66-4c8b-9f68-890324faf01e",
  "revision": 0,
  "last_node_id": 87,
  "last_link_id": 57,
  "nodes": [
    {
      "id": 78,
      "type": "Note",
      "pos": [
        18,
        -46
      ],
      "size": [
        210,
        88
      ],
      "flags": {},
      "order": 0,
      "mode": 0,
      "inputs": [],
      "outputs": [],
      "properties": {
        "text": ""
      },
      "widgets_values": [
        "You can write prompt here\n（你可以在此填写提示词）"
      ],
      "color": "#432",
      "bgcolor": "#653"
    },
    {
      "id": 75,
      "type": "FunTextBox",
      "pos": [
        250,
        -50
      ],
      "size": [
        383.54010009765625,
        156.71620178222656
      ],
      "flags": {},
      "order": 1,
      "mode": 0,
      "inputs": [],
      "outputs": [
        {
          "name": "prompt",
          "type": "STRING_PROMPT",
          "slot_index": 0,
          "links": [
            55
          ]
        }
      ],
      "title": "Positive Prompt（正向提示词）",
      "properties": {
        "Node name for S&R": "FunTextBox"
      },
      "widgets_values": [
        "fireworks display over night city. The video is of high quality, and the view is very clear. High quality, masterpiece, best quality, highres, ultra-detailed, fantastic."
      ]
    },
    {
      "id": 17,
      "type": "VHS_VideoCombine",
      "pos": [
        1126,
        -73
      ],
      "size": [
        390.9534912109375,
        538.0116577148438
      ],
      "flags": {},
      "order": 6,
      "mode": 0,
      "inputs": [
        {
          "label": "图像",
          "name": "images",
          "shape": 7,
          "type": "IMAGE",
          "link": 54
        },
        {
          "label": "音频",
          "name": "audio",
          "shape": 7,
          "type": "AUDIO",
          "link": null
        },
        {
          "label": "批次管理",
          "name": "meta_batch",
          "shape": 7,
          "type": "VHS_BatchManager",
          "link": null
        },
        {
          "name": "vae",
          "shape": 7,
          "type": "VAE",
          "link": null
        }
      ],
      "outputs": [
        {
          "label": "文件名",
          "name": "Filenames",
          "type": "VHS_FILENAMES",
          "slot_index": 0,
          "links": null
        }
      ],
      "properties": {
        "Node name for S&R": "VHS_VideoCombine"
      },
      "widgets_values": {
        "frame_rate": 16,
        "loop_count": 0,
        "filename_prefix": "Fun",
        "format": "video/h264-mp4",
        "pix_fmt": "yuv420p",
        "crf": 22,
        "save_metadata": true,
        "pingpong": false,
        "save_output": true,
        "videopreview": {
          "hidden": false,
          "paused": false,
          "params": {
            "filename": "Fun_00008.mp4",
            "subfolder": "",
            "type": "output",
            "format": "video/h264-mp4",
            "frame_rate": 16
          }
        }
      }
    },
    {
      "id": 73,
      "type": "FunTextBox",
      "pos": [
        250,
        160
      ],
      "size": [
        383.7149963378906,
        183.83506774902344
      ],
      "flags": {},
      "order": 2,
      "mode": 0,
      "inputs": [],
      "outputs": [
        {
          "name": "prompt",
          "type": "STRING_PROMPT",
          "slot_index": 0,
          "links": [
            56
          ]
        }
      ],
      "title": "Negtive Prompt（反向提示词）",
      "properties": {
        "Node name for S&R": "FunTextBox"
      },
      "widgets_values": [
        "色调艳丽，过曝，静态，细节模糊不清，字幕，风格，作品，画作，画面，静止，整体发灰，最差质量，低质量，JPEG压缩残留，丑陋的，残缺的，多余的手指，画得不好的手部，画得不好的脸部，畸形的，毁容的，形态畸形的肢体，手指融合，静止不动的画面，杂乱的背景，三条腿，背景人很多，倒着走"
      ]
    },
    {
      "id": 87,
      "type": "LoadWan2_2Model",
      "pos": [
        305.3617858886719,
        -300.4237060546875
      ],
      "size": [
        276.705078125,
        130
      ],
      "flags": {},
      "order": 3,
      "mode": 0,
      "inputs": [],
      "outputs": [
        {
          "name": "funmodels",
          "type": "FunModels",
          "links": [
            57
          ]
        }
      ],
      "properties": {
        "Node name for S&R": "LoadWan2_2Model"
      },
      "widgets_values": [
        "Wan2.2-T2V-A14B",
        "sequential_cpu_offload",
        "wan2.2/wan_civitai_t2v.yaml",
        "fp16"
      ]
    },
    {
      "id": 86,
      "type": "Wan2_2T2VSampler",
      "pos": [
        746.95556640625,
        -69.9979248046875
      ],
      "size": [
        312.3404235839844,
        430
      ],
      "flags": {},
      "order": 5,
      "mode": 0,
      "inputs": [
        {
          "name": "funmodels",
          "type": "FunModels",
          "link": 57
        },
        {
          "name": "prompt",
          "type": "STRING_PROMPT",
          "link": 55
        },
        {
          "name": "negative_prompt",
          "type": "STRING_PROMPT",
          "link": 56
        },
        {
          "name": "riflex_k",
          "shape": 7,
          "type": "RIFLEXT_ARGS",
          "link": null
        }
      ],
      "outputs": [
        {
          "name": "images",
          "type": "IMAGE",
          "links": [
            54
          ]
        }
      ],
      "properties": {
        "Node name for S&R": "Wan2_2T2VSampler"
      },
      "widgets_values": [
        81,
        832,
        480,
        false,
        43,
        "fixed",
        50,
        6,
        "Flow",
        0.15000000000000002,
        true,
        5,
        true,
        0
      ]
    },
    {
      "id": 80,
      "type": "Note",
      "pos": [
        -92,
        -294
      ],
      "size": [
        351.1499938964844,
        130.12660217285156
      ],
      "flags": {},
      "order": 4,
      "mode": 0,
      "inputs": [],
      "outputs": [],
      "properties": {
        "text": ""
      },
      "widgets_values": [
        "When using the 14B model, you can use sequential_cpu_offload to save GPU memory during generation.\n（在使用14B模型时，可以使用sequential_cpu_offload节省显存，进行生成。）"
      ],
      "color": "#432",
      "bgcolor": "#653"
    }
  ],
  "links": [
    [
      54,
      86,
      0,
      17,
      0,
      "IMAGE"
    ],
    [
      55,
      75,
      0,
      86,
      1,
      "STRING_PROMPT"
    ],
    [
      56,
      73,
      0,
      86,
      2,
      "STRING_PROMPT"
    ],
    [
      57,
      87,
      0,
      86,
      0,
      "FunModels"
    ]
  ],
  "groups": [
    {
      "id": 1,
      "title": "Load Model",
      "bounding": [
        220,
        -380,
        472,
        232
      ],
      "color": "#b06634",
      "font_size": 24,
      "flags": {}
    },
    {
      "id": 2,
      "title": "Prompts",
      "bounding": [
        218,
        -127,
        450,
        483
      ],
      "color": "#3f789e",
      "font_size": 24,
      "flags": {}
    }
  ],
  "config": {},
  "extra": {
    "ds": {
      "scale": 0.9090909090909091,
      "offset": [
        149.60461329280074,
        495.60652716079886
      ]
    },
    "workspace_info": {
      "id": "776b62b4-bd17-4ed3-9923-b7aad000b1ea"
    },
    "node_versions": {
      "CogVideoX-Fun": "ffe64f2b8c101da85e0707c59b355f21a83f5464",
      "ComfyUI-VideoHelperSuite": "70faa9bcef65932ab72e7404d6373fb300013a2e"
    },
    "frontendVersion": "1.21.3"
  },
  "version": 0.4
}